voxtus/__init__.py
voxtus/__main__.py
voxtus/formats/__init__.py
voxtus/formats/json.py
voxtus/formats/srt.py
voxtus/formats/txt.py
voxtus/formats/vtt.py
voxtus-0.3.2.dist-info/licenses/LICENSE
voxtus-0.3.2.dist-info/METADATA
voxtus-0.3.2.dist-info/WHEEL
voxtus-0.3.2.dist-info/entry_points.txt
voxtus-0.3.2.dist-info/top_level.txt
voxtus-0.3.2.dist-info/RECORD
