Metadata-Version: 2.4
Name: voxtus
Version: 0.3.2
Summary: [DEPRECATED - Use 'cargo install voxtus' instead] Transcribe Internet videos and media files to text
Author-email: Johan Thorén <johan@thoren.xyz>
License: AGPL-3.0-or-later
Requires-Python: >=3.9
License-File: LICENSE
Requires-Dist: faster-whisper==1.1.1
Requires-Dist: yt-dlp==2025.5.22
Requires-Dist: returns
Provides-Extra: test
Requires-Dist: pytest; extra == "test"
Requires-Dist: pytest-xdist; extra == "test"
Requires-Dist: pytest-cov; extra == "test"
Provides-Extra: dev
Requires-Dist: pytest; extra == "dev"
Requires-Dist: pytest-xdist; extra == "dev"
Requires-Dist: pytest-cov; extra == "dev"
Requires-Dist: build; extra == "dev"
Requires-Dist: twine; extra == "dev"
Dynamic: license-file
